{
	"courses": [
		{
			"layup_url": "https://www.layuplist.com/course/4455",
			"layup_id": 4455,
			"title": "ENVS092: Thesis Research in Environmental Studies II",
			"department": "ENVS",
			"offered": true,
			"distribs": null,
			"total_reviews": 0,
			"quality_score": 0,
			"layup_score": 0
		},
		{
			"layup_url": "https://www.layuplist.com/course/3037",
			"layup_id": 3037,
			"title": "ENVS007.02: Conservation\u0026Sustainability",
			"department": "ENVS",
			"offered": true,
			"distribs": [
				"INT"
			],
			"total_reviews": 1,
			"quality_score": -1,
			"layup_score": 0
		},
		{
			"layup_url": "https://www.layuplist.com/course/1207",
			"layup_id": 1207,
			"title": "ENVS050: Environmental Problem Analysis and Policy Formulation",
			"department": "ENVS",
			"offered": false,
			"distribs": [
				"SOC"
			],
			"total_reviews": 4,
			"quality_score": 2,
			"layup_score": 1
		},
		{
			"layup_url": "https://www.layuplist.com/course/3734",
			"layup_id": 3734,
			"title": "ENVS007.11: Low Carbon Society",
			"department": "ENVS",
			"offered": false,
			"distribs": [
				"INT",
				"SOC"
			],
			"total_reviews": 0,
			"quality_score": 0,
			"layup_score": 0
		},
		{
			"layup_url": "https://www.layuplist.com/course/3091",
			"layup_id": 3091,
			"title": "ENVS007.12: Writing Natural History",
			"department": "ENVS",
			"offered": false,
			"distribs": [
				"SCI"
			],
			"total_reviews": 0,
			"quality_score": 0,
			"layup_score": 0
		},
		{
			"layup_url": "https://www.layuplist.com/course/1187",
			"layup_id": 1187,
			"title": "ENVS002: Introduction to Environmental Science",
			"department": "ENVS",
			"offered": true,
			"distribs": [
				"SCI"
			],
			"total_reviews": 151,
			"quality_score": 24,
			"layup_score": 3
		},
		{
			"layup_url": "https://www.layuplist.com/course/3038",
			"layup_id": 3038,
			"title": "ENVS007.03: Ecopsychology",
			"department": "ENVS",
			"offered": false,
			"distribs": [
				"TMV"
			],
			"total_reviews": 0,
			"quality_score": 1,
			"layup_score": 0
		},
		{
			"layup_url": "https://www.layuplist.com/course/1188",
			"layup_id": 1188,
			"title": "ENVS003: Environment and Society: Towards Sustainability?",
			"department": "ENVS",
			"offered": false,
			"distribs": [
				"SOC"
			],
			"total_reviews": 45,
			"quality_score": 9,
			"layup_score": 7
		},
		{
			"layup_url": "https://www.layuplist.com/course/1208",
			"layup_id": 1208,
			"title": "ENVS053: Science for Sustainable Systems",
			"department": "ENVS",
			"offered": false,
			"distribs": null,
			"total_reviews": 2,
			"quality_score": 1,
			"layup_score": 1
		},
		{
			"layup_url": "https://www.layuplist.com/course/1197",
			"layup_id": 1197,
			"title": "ENVS019: Encountering Forests",
			"department": "ENVS",
			"offered": false,
			"distribs": null,
			"total_reviews": 0,
			"quality_score": 0,
			"layup_score": 1
		},
		{
			"layup_url": "https://www.layuplist.com/course/1196",
			"layup_id": 1196,
			"title": "ENVS018: Indigenous Environmental Studies",
			"department": "ENVS",
			"offered": false,
			"distribs": [
				"TMV",
				"NW"
			],
			"total_reviews": 0,
			"quality_score": 5,
			"layup_score": 3
		},
		{
			"layup_url": "https://www.layuplist.com/course/1202",
			"layup_id": 1202,
			"title": "ENVS039: Natural Resources, Development, and the Environment",
			"department": "ENVS",
			"offered": false,
			"distribs": [
				"SOC"
			],
			"total_reviews": 22,
			"quality_score": 2,
			"layup_score": 3
		},
		{
			"layup_url": "https://www.layuplist.com/course/1198",
			"layup_id": 1198,
			"title": "ENVS020: Conservation of Biodiversity",
			"department": "ENVS",
			"offered": false,
			"distribs": [
				"TAS"
			],
			"total_reviews": 21,
			"quality_score": 3,
			"layup_score": 0
		},
		{
			"layup_url": "https://www.layuplist.com/course/3089",
			"layup_id": 3089,
			"title": "ENVS007.04: COVER Stories",
			"department": "ENVS",
			"offered": false,
			"distribs": [
				"SOC"
			],
			"total_reviews": 1,
			"quality_score": 4,
			"layup_score": 0
		},
		{
			"layup_url": "https://www.layuplist.com/course/1209",
			"layup_id": 1209,
			"title": "ENVS055: Ecological Economics",
			"department": "ENVS",
			"offered": true,
			"distribs": [
				"SOC"
			],
			"total_reviews": 2,
			"quality_score": 3,
			"layup_score": 2
		},
		{
			"layup_url": "https://www.layuplist.com/course/1199",
			"layup_id": 1199,
			"title": "ENVS025: Ecological Agriculture",
			"department": "ENVS",
			"offered": false,
			"distribs": [
				"TLA"
			],
			"total_reviews": 22,
			"quality_score": 6,
			"layup_score": 4
		},
		{
			"layup_url": "https://www.layuplist.com/course/1203",
			"layup_id": 1203,
			"title": "ENVS040: Foreign Study in Environmental Problems I",
			"department": "ENVS",
			"offered": false,
			"distribs": [
				"SOC"
			],
			"total_reviews": 5,
			"quality_score": 1,
			"layup_score": 1
		},
		{
			"layup_url": "https://www.layuplist.com/course/4142",
			"layup_id": 4142,
			"title": "ENVS007.13: Putting a Price on the Planet",
			"department": "ENVS",
			"offered": false,
			"distribs": [
				"SOC"
			],
			"total_reviews": 1,
			"quality_score": 2,
			"layup_score": 1
		},
		{
			"layup_url": "https://www.layuplist.com/course/1200",
			"layup_id": 1200,
			"title": "ENVS028: Global Environmental Health",
			"department": "ENVS",
			"offered": false,
			"distribs": [
				"TAS"
			],
			"total_reviews": 17,
			"quality_score": 6,
			"layup_score": 1
		},
		{
			"layup_url": "https://www.layuplist.com/course/1219",
			"layup_id": 1219,
			"title": "ENVS080.02: Writing Our Way Home: The Writing that Sustains Us",
			"department": "ENVS",
			"offered": false,
			"distribs": [
				"LIT",
				"CI"
			],
			"total_reviews": 0,
			"quality_score": 1,
			"layup_score": 0
		},
		{
			"layup_url": "https://www.layuplist.com/course/1201",
			"layup_id": 1201,
			"title": "ENVS030: Global Environmental Science",
			"department": "ENVS",
			"offered": false,
			"distribs": [
				"SCI"
			],
			"total_reviews": 10,
			"quality_score": 4,
			"layup_score": 2
		},
		{
			"layup_url": "https://www.layuplist.com/course/1220",
			"layup_id": 1220,
			"title": "ENVS080.03: Regenerative Design of the Built Environment",
			"department": "ENVS",
			"offered": true,
			"distribs": null,
			"total_reviews": 0,
			"quality_score": 0,
			"layup_score": 0
		},
		{
			"layup_url": "https://www.layuplist.com/course/1191",
			"layup_id": 1191,
			"title": "ENVS011: Humans and Nature in America",
			"department": "ENVS",
			"offered": false,
			"distribs": [
				"LIT",
				"W"
			],
			"total_reviews": 0,
			"quality_score": 1,
			"layup_score": 1
		},
		{
			"layup_url": "https://www.layuplist.com/course/1204",
			"layup_id": 1204,
			"title": "ENVS042: Foreign Study in Environmental Problems II",
			"department": "ENVS",
			"offered": false,
			"distribs": [
				"INT"
			],
			"total_reviews": 4,
			"quality_score": 1,
			"layup_score": 1
		},
		{
			"layup_url": "https://www.layuplist.com/course/1192",
			"layup_id": 1192,
			"title": "ENVS012: Energy and the Environment",
			"department": "ENVS",
			"offered": true,
			"distribs": [
				"TAS"
			],
			"total_reviews": 29,
			"quality_score": 11,
			"layup_score": 7
		},
		{
			"layup_url": "https://www.layuplist.com/course/1214",
			"layup_id": 1214,
			"title": "ENVS067: Political Ecology",
			"department": "ENVS",
			"offered": false,
			"distribs": [
				"INT",
				"SOC"
			],
			"total_reviews": 0,
			"quality_score": 4,
			"layup_score": 3
		},
		{
			"layup_url": "https://www.layuplist.com/course/1215",
			"layup_id": 1215,
			"title": "ENVS070: Environmental Policy Research Workshop",
			"department": "ENVS",
			"offered": false,
			"distribs": null,
			"total_reviews": 0,
			"quality_score": 0,
			"layup_score": 1
		},
		{
			"layup_url": "https://www.layuplist.com/course/4827",
			"layup_id": 4827,
			"title": "ENVS007.14: Hidden From View",
			"department": "ENVS",
			"offered": false,
			"distribs": [
				"SOC"
			],
			"total_reviews": 0,
			"quality_score": 2,
			"layup_score": 0
		},
		{
			"layup_url": "https://www.layuplist.com/course/1217",
			"layup_id": 1217,
			"title": "ENVS079: The Soil Resource",
			"department": "ENVS",
			"offered": false,
			"distribs": [
				"SLA"
			],
			"total_reviews": 1,
			"quality_score": 1,
			"layup_score": 1
		},
		{
			"layup_url": "https://www.layuplist.com/course/1205",
			"layup_id": 1205,
			"title": "ENVS044: Environment and Politics in Southeast Asia",
			"department": "ENVS",
			"offered": false,
			"distribs": [
				"NW",
				"INT",
				"SOC"
			],
			"total_reviews": 28,
			"quality_score": 1,
			"layup_score": 1
		},
		{
			"layup_url": "https://www.layuplist.com/course/1193",
			"layup_id": 1193,
			"title": "ENVS015: Environmental Issues of the Earth's Cold Regions",
			"department": "ENVS",
			"offered": false,
			"distribs": [
				"TAS"
			],
			"total_reviews": 18,
			"quality_score": 3,
			"layup_score": 7
		},
		{
			"layup_url": "https://www.layuplist.com/course/1210",
			"layup_id": 1210,
			"title": "ENVS056: Environmental Economics and Governance",
			"department": "ENVS",
			"offered": false,
			"distribs": [
				"SOC"
			],
			"total_reviews": 2,
			"quality_score": 1,
			"layup_score": 1
		},
		{
			"layup_url": "https://www.layuplist.com/course/1218",
			"layup_id": 1218,
			"title": "ENVS080.01: Arctic Environmental Change",
			"department": "ENVS",
			"offered": true,
			"distribs": [
				"TAS"
			],
			"total_reviews": 0,
			"quality_score": 0,
			"layup_score": 0
		},
		{
			"layup_url": "https://www.layuplist.com/course/1189",
			"layup_id": 1189,
			"title": "ENVS007: First-Year Seminars in Environmental Studies",
			"department": "ENVS",
			"offered": false,
			"distribs": null,
			"total_reviews": 69,
			"quality_score": 11,
			"layup_score": 1
		},
		{
			"layup_url": "https://www.layuplist.com/course/1216",
			"layup_id": 1216,
			"title": "ENVS072: Nature Writers",
			"department": "ENVS",
			"offered": false,
			"distribs": [
				"LIT",
				"W"
			],
			"total_reviews": 3,
			"quality_score": 1,
			"layup_score": 1
		},
		{
			"layup_url": "https://www.layuplist.com/course/1206",
			"layup_id": 1206,
			"title": "ENVS045: Colonialism, Development and the Environment in Africa and Asia",
			"department": "ENVS",
			"offered": true,
			"distribs": [
				"INT",
				"SOC",
				"NW"
			],
			"total_reviews": 0,
			"quality_score": 0,
			"layup_score": 1
		},
		{
			"layup_url": "https://www.layuplist.com/course/1221",
			"layup_id": 1221,
			"title": "ENVS080.08: The Practice of Science Policy \u0026 Diplomacy",
			"department": "ENVS",
			"offered": false,
			"distribs": [
				"SOC"
			],
			"total_reviews": 1,
			"quality_score": 2,
			"layup_score": 3
		},
		{
			"layup_url": "https://www.layuplist.com/course/1211",
			"layup_id": 1211,
			"title": "ENVS060: Environmental Law",
			"department": "ENVS",
			"offered": false,
			"distribs": [
				"SOC"
			],
			"total_reviews": 20,
			"quality_score": 4,
			"layup_score": 3
		},
		{
			"layup_url": "https://www.layuplist.com/course/1194",
			"layup_id": 1194,
			"title": "ENVS016: Business, Growth, and the Environment",
			"department": "ENVS",
			"offered": false,
			"distribs": [
				"INT",
				"SOC"
			],
			"total_reviews": 2,
			"quality_score": 2,
			"layup_score": 1
		},
		{
			"layup_url": "https://www.layuplist.com/course/1195",
			"layup_id": 1195,
			"title": "ENVS017: Marine Policy",
			"department": "ENVS",
			"offered": false,
			"distribs": [
				"SOC"
			],
			"total_reviews": 2,
			"quality_score": 3,
			"layup_score": 1
		},
		{
			"layup_url": "https://www.layuplist.com/course/1190",
			"layup_id": 1190,
			"title": "ENVS010: Introduction to Environmental Statistics",
			"department": "ENVS",
			"offered": false,
			"distribs": [
				"QDS"
			],
			"total_reviews": 0,
			"quality_score": 0,
			"layup_score": 1
		},
		{
			"layup_url": "https://www.layuplist.com/course/1223",
			"layup_id": 1223,
			"title": "ENVS084: Seminar on Environmental Issues of Southern Africa",
			"department": "ENVS",
			"offered": false,
			"distribs": [
				"NW"
			],
			"total_reviews": 4,
			"quality_score": 1,
			"layup_score": 1
		},
		{
			"layup_url": "https://www.layuplist.com/course/1225",
			"layup_id": 1225,
			"title": "ENVS090: Independent Study and Research",
			"department": "ENVS",
			"offered": true,
			"distribs": null,
			"total_reviews": 0,
			"quality_score": 0,
			"layup_score": 1
		},
		{
			"layup_url": "https://www.layuplist.com/course/1212",
			"layup_id": 1212,
			"title": "ENVS061: Governing the Environment",
			"department": "ENVS",
			"offered": true,
			"distribs": [
				"SOC"
			],
			"total_reviews": 0,
			"quality_score": 1,
			"layup_score": 0
		},
		{
			"layup_url": "https://www.layuplist.com/course/5118",
			"layup_id": 5118,
			"title": "ENVS080.10: Coupled Human-Natural Systs",
			"department": "ENVS",
			"offered": true,
			"distribs": [
				"QDS"
			],
			"total_reviews": 0,
			"quality_score": 0,
			"layup_score": 0
		},
		{
			"layup_url": "https://www.layuplist.com/course/1222",
			"layup_id": 1222,
			"title": "ENVS083: Environmental Social Science Research Methods",
			"department": "ENVS",
			"offered": false,
			"distribs": null,
			"total_reviews": 0,
			"quality_score": 0,
			"layup_score": 1
		},
		{
			"layup_url": "https://www.layuplist.com/course/3991",
			"layup_id": 3991,
			"title": "ENVS080.09: Spatial Thinking in Ecology and Conservation",
			"department": "ENVS",
			"offered": false,
			"distribs": [
				"TAS"
			],
			"total_reviews": 0,
			"quality_score": 0,
			"layup_score": 0
		},
		{
			"layup_url": "https://www.layuplist.com/course/1213",
			"layup_id": 1213,
			"title": "ENVS065: Global Environmental Politics",
			"department": "ENVS",
			"offered": false,
			"distribs": [
				"INT"
			],
			"total_reviews": 25,
			"quality_score": 4,
			"layup_score": 0
		},
		{
			"layup_url": "https://www.layuplist.com/course/1226",
			"layup_id": 1226,
			"title": "ENVS091: Thesis Research in Environmental Studies I",
			"department": "ENVS",
			"offered": true,
			"distribs": null,
			"total_reviews": 0,
			"quality_score": 0,
			"layup_score": 1
		},
		{
			"layup_url": "https://www.layuplist.com/course/1224",
			"layup_id": 1224,
			"title": "ENVS089: Soils, Forests and Food",
			"department": "ENVS",
			"offered": false,
			"distribs": [
				"SCI"
			],
			"total_reviews": 2,
			"quality_score": 1,
			"layup_score": 1
		}
	],
	"updated": "2020-02-11 18:33:44",
	"total": 50
}